quiz/__init__.py
quiz/admin.py
quiz/apps.py
quiz/forms.py
quiz/models.py
quiz/tests.py
quiz/urls.py
quiz/views.py
quiz/fixtures/sample_quizzes.json
quiz/migrations/0001_initial.py
quiz/migrations/0002_answer_img_question_img_question_img_explanation.py
quiz/migrations/__init__.py
quiz/static/datatables/dataTables.bootstrap4.min.css
quiz/static/datatables/dataTables.bootstrap4.min.js
quiz/static/datatables/jquery.dataTables.min.js
quiz/static/quiz/app.css
quiz/static/quiz/bootstrap.min.css
quiz/static/quiz/jquery-3.3.1.min.js
quiz/templates/quiz/_header.html
quiz/templates/quiz/base.html
quiz/templates/quiz/interests_form.html
quiz/templates/quiz/quiz_list.html
quiz/templates/quiz/quiz_result.html
quiz/templates/quiz/student_detail.html
quiz/templates/quiz/student_list.html
quiz/templates/quiz/take_quiz_form.html
quiz/templates/quiz/taken_quiz_list.html
quiz/templatetags/__init__.py
quiz/templatetags/quiz_extras.py
django_mcq-0.4.dist-info/LICENSE
django_mcq-0.4.dist-info/METADATA
django_mcq-0.4.dist-info/WHEEL
django_mcq-0.4.dist-info/top_level.txt
django_mcq-0.4.dist-info/RECORD
